nimble_aws/__init__.py
nimble_aws/adapter/__init__.py
nimble_aws/adapter/api_gateway.py
nimble_aws/adapter/appsync.py
nimble_aws/adapter/cognito.py
nimble_aws/adapter/config.py
nimble_aws/adapter/dynamodb.py
nimble_aws/adapter/event_bridge.py
nimble_aws/adapter/glue.py
nimble_aws/adapter/lambda_serverless.py
nimble_aws/adapter/s3.py
nimble_aws/adapter/secrets_manager.py
nimble_aws/adapter/session.py
nimble_aws/adapter/sfn.py
nimble_aws/adapter/sns.py
nimble_aws/adapter/sqs.py
nimble_aws/adapter/utils.py
nimble_aws/middleware/__init__.py
nimble_aws/middleware/api_gateway.py
nimble_aws-0.1.1.dist-info/METADATA
nimble_aws-0.1.1.dist-info/WHEEL
nimble_aws-0.1.1.dist-info/RECORD
