Metadata-Version: 2.1
Name: nimble-aws
Version: 0.1.1
Summary: Nimble-AWS is a Python library engineered for high-performance, asynchronous communication with AWS services. The library focuses on providing streamlined adapters that abstract the complexity of AWS operations, making it easier to integrate AWS into your applications.
Author: Lucas Tiense Blazzi
Author-email: lucast.blazzi@gmail.com
Requires-Python: >=3.11,<4.0
Classifier: Programming Language :: Python :: 3
Classifier: Programming Language :: Python :: 3.11
Classifier: Programming Language :: Python :: 3.12
Classifier: Programming Language :: Python :: 3.13
Requires-Dist: aiobotocore (==2.13.1)
Requires-Dist: boto3 (>=1.17.47,<2.0.0)
Requires-Dist: pydantic (>=2.4.2,<3.0.0)
Requires-Dist: pydantic-settings (>=2.0.3,<3.0.0)
Requires-Dist: pyfunctional (>=1.4.3,<2.0.0)
